dlg_casacore_components/__init__.py
dlg_casacore_components/ms.py
dlg_casacore_components/plasma.py
dlg_casacore_components/sdp.py
dlg_casacore_components/taql.py
dlg_casacore_components-0.3.1.dist-info/LICENSE
dlg_casacore_components-0.3.1.dist-info/METADATA
dlg_casacore_components-0.3.1.dist-info/WHEEL
dlg_casacore_components-0.3.1.dist-info/entry_points.txt
dlg_casacore_components-0.3.1.dist-info/top_level.txt
dlg_casacore_components-0.3.1.dist-info/RECORD
