Metadata-Version: 2.1
Name: dlg-casacore-components
Version: 0.3.1
Summary: casacore components for daliuge-engine created by ICRAR
Home-page: https://github.com/ICRAR/dlg-casacore-components
Author: ICRAR DIA Group
Author-email: dfms_prototype@googlegroups.com
License: GNU General Public License v2 or later (GPLv2+)
Platform: UNKNOWN
License-File: LICENSE
Requires-Dist: daliuge-engine (>=2.1)
Requires-Dist: numpy (>=1.20.0)
Requires-Dist: pyarrow (>=3.0.0)
Requires-Dist: python-casacore (>=3.4.0)
Requires-Dist: ska-sdp-realtime-receive-modules[plasma] (>=2.0.2)
Requires-Dist: ska-sdp-realtime-receive-core[plasma] (>=2.0.2)
Provides-Extra: test
Requires-Dist: pytest ; extra == 'test'
Requires-Dist: coverage ; extra == 'test'
Requires-Dist: flake8 ; extra == 'test'
Requires-Dist: black ; extra == 'test'
Requires-Dist: isort ; extra == 'test'
Requires-Dist: pytest-cov ; extra == 'test'
Requires-Dist: codecov ; extra == 'test'
Requires-Dist: mypy ; extra == 'test'
Requires-Dist: gitchangelog ; extra == 'test'
Requires-Dist: mkdocs ; extra == 'test'
